LICENSE
MANIFEST.in
README.md
setup.py
pydiq/__init__.py
pydiq/app.py
pydiq/core.py
pydiq/dicom_data.py
pydiq/dicom_widget.py
pydiq/utils.py
pydiq/viewer.py
pydiq.egg-info/PKG-INFO
pydiq.egg-info/SOURCES.txt
pydiq.egg-info/dependency_links.txt
pydiq.egg-info/entry_points.txt
pydiq.egg-info/requires.txt
pydiq.egg-info/top_level.txt