Metadata-Version: 2.1
Name: pydiq
Version: 0.2.2
Summary: Simple open-source DICOM browser/viewer in Python and Qt4.
Home-page: https://github.com/janpipek/pydiq
Author: Jan Pipek
Author-email: jan.pipek@gmail.com
License: MIT
Platform: UNKNOWN
Requires-Python: >=3.6
